CADS/__init__.py
CADS/__main__.py
CADS/DATA/LOGO.gif
CADS/Database/CMEMS_Database.json
CADS/Database/CMEMS_Databaseselvar.json
CADS/Database/datasets_MY.pdf
CADS/Script/CMEMS_Database.json
CADS/Script/FTPsubsetMO.py
CADS-0.0.4.dist-info/LICENSE
CADS-0.0.4.dist-info/METADATA
CADS-0.0.4.dist-info/WHEEL
CADS-0.0.4.dist-info/entry_points.txt
CADS-0.0.4.dist-info/top_level.txt
CADS-0.0.4.dist-info/RECORD
